biodome.py
biodome-2022.9.1.dist-info/LICENSE
biodome-2022.9.1.dist-info/WHEEL
biodome-2022.9.1.dist-info/METADATA
biodome-2022.9.1.dist-info/RECORD
